pyfas/__init__.py
pyfas/genkey.py
pyfas/gists.py
pyfas/pilink.py
pyfas/ppl.py
pyfas/sfc.py
pyfas/tab.py
pyfas/tpl.py
pyfas/usc.py
pyfas/test/__init__.py
pyfas/test/test_gists.py
pyfas/test/test_ppl.py
pyfas/test/test_sfc.py
pyfas/test/test_tab.py
pyfas/test/test_tpl.py
pyfas/test/test_usc.py
pyfas-0.4.3.dist-info/LICENSE.txt
pyfas-0.4.3.dist-info/METADATA
pyfas-0.4.3.dist-info/WHEEL
pyfas-0.4.3.dist-info/top_level.txt
pyfas-0.4.3.dist-info/RECORD
