Metadata-Version: 2.1
Name: pyfas
Version: 0.4.3
Summary: Toolbox for Flow Assurance engineers
Author-email: Giuseppe Pagliuca <giuseppe.pagliuca@gmail.com>
License: GNU GENERAL PUBLIC LICENSE
Project-URL: Homepage, https://github.com/gpagliuca/pyfas
Keywords: flow,engineering,toolbox
Classifier: License :: OSI Approved :: MIT License
Classifier: Programming Language :: Python
Classifier: Programming Language :: Python :: 3
Requires-Python: >=3.6
License-File: LICENSE.txt
Requires-Dist: pandas
